design.sv
// Code your design here
module sync_ram(
  input clk,
  input we,
  input [2:0] addr,
  input [7:0] din,
  output reg [7:0] dout);
  
  reg [7:0] mem [0:7];
  always @(posedge clk) begin
    if(we)
      mem[addr] <= din;
    else
      dout <= mem[addr];
  end
  endmodule

testbench.sv
// Code your testbench here
// or browse Examples
module tb_sync_ram;
  reg clk;
  reg we;
  reg [2:0] addr;
  reg [7:0] din;
  wire [7:0] dout;
  
  sync_ram uut ( 
    .clk(clk),
    .we(we),
    .addr(addr),
    .din(din),
    .dout(dout)
  );
  always #5 clk = ~clk;
    initial begin
      $monitor("Time = %0t | WE = %b | Addr = %d | DIN = %h | DOUT = %h", $time, we, addr, din, dout);
      $dumpfile("sync_ram.vcd");
      $dumpvars;
      clk = 0;
      we = 1;
      addr = 3'b000; din = 8'hAA; #10;
      addr = 3'b001; din = 8'h55; #10;
      addr = 3'b010; din = 8'hF0; #10;
      we = 0;
      addr = 3'b000; #10;
      addr = 3'b001; #10;
      addr = 3'b010; #10;
      $finish;
    end 
endmodule

sync_ram.vcd
$date
	Wed Jul  9 06:03:07 2025
$end
$version
	Icarus Verilog
$end
$timescale
	1s
$end
$scope module tb_sync_ram $end
$var wire 8 ! dout [7:0] $end
$var reg 3 " addr [2:0] $end
$var reg 1 # clk $end
$var reg 8 $ din [7:0] $end
$var reg 1 % we $end
$scope module uut $end
$var wire 3 & addr [2:0] $end
$var wire 1 # clk $end
$var wire 8 ' din [7:0] $end
$var wire 1 % we $end
$var reg 8 ( dout [7:0] $end
$upscope $end
$upscope $end
$enddefinitions $end
$comment Show the parameter values. $end
$dumpall
$end
#0
$dumpvars
bx (
b10101010 '
b0 &
1%
b10101010 $
0#
b0 "
bx !
$end
#5
1#
#10
0#
b1010101 $
b1010101 '
b1 "
b1 &
#15
1#
#20
0#
b11110000 $
b11110000 '
b10 "
b10 &
#25
1#
#30
0#
b0 "
b0 &
0%
#35
b10101010 !
b10101010 (
1#
#40
0#
b1 "
b1 &
#45
b1010101 !
b1010101 (
1#
#50
0#
b10 "
b10 &
#55
b11110000 !
b11110000 (
1#
